MANIFEST.in
setup.cfg
setup.py
src/nd_image.c
src/nd_image.h
src/ni_filters.c
src/ni_filters.h
src/ni_fourier.c
src/ni_fourier.h
src/ni_interpolation.c
src/ni_interpolation.h
src/ni_measure.c
src/ni_measure.h
src/ni_morphology.c
src/ni_morphology.h
src/ni_support.c
src/ni_support.h
stsci/__init__.py
stsci.ndimage.egg-info/PKG-INFO
stsci.ndimage.egg-info/SOURCES.txt
stsci.ndimage.egg-info/dependency_links.txt
stsci.ndimage.egg-info/namespace_packages.txt
stsci.ndimage.egg-info/not-zip-safe
stsci.ndimage.egg-info/requires.txt
stsci.ndimage.egg-info/top_level.txt
stsci/ndimage/__init__.py
stsci/ndimage/_ni_support.py
stsci/ndimage/doccer.py
stsci/ndimage/filters.py
stsci/ndimage/fourier.py
stsci/ndimage/info.py
stsci/ndimage/interpolation.py
stsci/ndimage/io.py
stsci/ndimage/measurements.py
stsci/ndimage/morphology.py
stsci/ndimage/version.py
stsci/ndimage/tests/__init__.py
stsci/ndimage/tests/dots.png
stsci/ndimage/tests/test_filters.py
stsci/ndimage/tests/test_io.py
stsci/ndimage/tests/test_measurements.py
stsci/ndimage/tests/test_ndimage.py
stsci/ndimage/tests/test_regression.py