Metadata-Version: 1.1
Name: stsci.ndimage
Version: 0.10.3
Summary: Various functions for multi-dimensional image processing--fork of
Home-page: http://www.stsci.edu/resources/software_hardware/stsci_python
Author: STScI
Author-email: help@stsci.edu
License: UNKNOWN
Platform: UNKNOWN
Classifier: Intended Audience :: Science/Research
Classifier: License :: OSI Approved :: BSD License
Classifier: Operating System :: OS Independent
Classifier: Programming Language :: Python
Classifier: Topic :: Scientific/Engineering :: Astronomy
Classifier: Topic :: Software Development :: Libraries :: Python Modules
